telebaka_inspector/__init__.py
telebaka_inspector/admin.py
telebaka_inspector/bot.py
telebaka_inspector/models.py
telebaka_inspector/urls.py
telebaka_inspector/views.py
telebaka_inspector/migrations/0001_initial.py
telebaka_inspector/migrations/__init__.py
telebaka_inspector-0.1.dist-info/METADATA
telebaka_inspector-0.1.dist-info/RECORD
telebaka_inspector-0.1.dist-info/WHEEL
telebaka_inspector-0.1.dist-info/top_level.txt
